shelfquery/__init__.py
shelfquery-3.3.2.dist-info/LICENSE
shelfquery-3.3.2.dist-info/METADATA
shelfquery-3.3.2.dist-info/WHEEL
shelfquery-3.3.2.dist-info/top_level.txt
shelfquery-3.3.2.dist-info/RECORD
