Metadata-Version: 2.1
Name: shelfquery
Version: 3.3.2
Summary: shelfdb query client.
Home-page: https://github.com/nitipit/shelfquery
Author: Nitipit Nontasuwan
Author-email: nitipit@gmail.com
Keywords: shelfdb database query
Classifier: Programming Language :: Python :: 3
Classifier: License :: OSI Approved :: MIT License
Classifier: Operating System :: OS Independent
Requires-Python: >=3.10.0
License-File: LICENSE
Requires-Dist: dill (>=0.3.3)
